kraken_biom.py
kraken_biom-1.0.1.dist-info/DESCRIPTION.rst
kraken_biom-1.0.1.dist-info/METADATA
kraken_biom-1.0.1.dist-info/RECORD
kraken_biom-1.0.1.dist-info/WHEEL
kraken_biom-1.0.1.dist-info/entry_points.txt
kraken_biom-1.0.1.dist-info/metadata.json
kraken_biom-1.0.1.dist-info/namespace_packages.txt
kraken_biom-1.0.1.dist-info/top_level.txt
