Metadata-Version: 2.0
Name: kraken-biom
Version: 1.0.1
Summary: Create BIOM-format tables from Kraken output.
Home-page: https://github.com/smdabdoub/kraken-biom
Author: Shareef M. Dabdoub
Author-email: dabdoub.2@osu.edu
License: MIT
Keywords: kraken,BIOM,metagenomics,bioinformatics,taxonomy
Platform: UNKNOWN
Classifier: Development Status :: 4 - Beta
Classifier: Environment :: Console
Classifier: Intended Audience :: Science/Research
Classifier: License :: OSI Approved :: MIT License
Classifier: Operating System :: OS Independent
Classifier: Programming Language :: Python
Classifier: Programming Language :: Python :: 2
Classifier: Programming Language :: Python :: 3
Classifier: Topic :: Scientific/Engineering :: Bio-Informatics
Requires-Dist: biom-format (>=2.1.5)
